code/DFF.v
// D Flip Flop - without Clear

`default_nettype none
`timescale 1ns/1ps

module DFF(output reg Q, input D, input clk);
    always@(posedge clk) begin
       Q <= D;       
    end
endmodule

code/DFF_tb.v
`timescale 1ns/1ps

module DFF_tb;

    // 1. Declare signals
    reg D;
    reg clk;
    wire Q;

    // 2. Instantiate the Unit Under Test (UUT)
    DFF uut (
        .Q(Q), 
        .D(D), 
        .clk(clk)
    );

    // 3. Generate the Clock (10ns period -> 100MHz)
    always begin
        #5 clk = ~clk; 
    end

    // 4. Stimulus block
    initial begin
        // Initialize inputs
        clk = 0;
        D = 0;

        // Wait for global reset (if any)
        #10;
        
        // Test Case 1: Set D to 1
        D = 1;
        #10; // Wait for one clock cycle
        
        // Test Case 2: Set D back to 0
        D = 0;
        #10;
        
        // Test Case 3: Rapid changes (D changes between clock edges)
        #2 D = 1;
        #2 D = 0;
        #10;

        $display("Simulation finished.");
        $finish;
    end

    // 5. (Optional) Create a waveform file
    initial begin
        $dumpfile("dff_test.vcd");
        $dumpvars(0, DFF_tb);
    end

endmodule

code/dff_test.vcd
$date
	Fri Feb  6 08:26:14 2026
$end
$version
	Icarus Verilog
$end
$timescale
	1ps
$end
$scope module DFF_tb $end
$var wire 1 ! Q $end
$var reg 1 " D $end
$var reg 1 # clk $end
$scope module uut $end
$var wire 1 " D $end
$var wire 1 # clk $end
$var reg 1 ! Q $end
$upscope $end
$upscope $end
$enddefinitions $end
$comment Show the parameter values. $end
$dumpall
$end
#0
$dumpvars
0#
0"
x!
$end
#5000
0!
1#
#10000
0#
1"
#15000
1!
1#
#20000
0#
0"
#25000
0!
1#
#30000
0#
#32000
1"
#34000
0"
